tests/test_identical.py
tests/test_module.py
tests/test_module_autograd.py
tests/test_objective.py
tests/test_opts.py
tests/test_tensorlist.py
tests/test_utils_optimizer.py
torchzero/__init__.py
torchzero/_minimize/__init__.py
torchzero/_minimize/methods.py
torchzero/_minimize/minimize.py
torchzero/core/__init__.py
torchzero/core/chain.py
torchzero/core/functional.py
torchzero/core/modular.py
torchzero/core/module.py
torchzero/core/objective.py
torchzero/core/reformulation.py
torchzero/core/transform.py
torchzero/linalg/__init__.py
torchzero/linalg/benchmark.py
torchzero/linalg/eigh.py
torchzero/linalg/linalg_utils.py
torchzero/linalg/linear_operator.py
torchzero/linalg/matrix_power.py
torchzero/linalg/orthogonalize.py
torchzero/linalg/qr.py
torchzero/linalg/sketch.py
torchzero/linalg/solve.py
torchzero/linalg/svd.py
torchzero/linalg/torch_linalg.py
torchzero/modules/__init__.py
torchzero/modules/opt_utils.py
torchzero/modules/adaptive/__init__.py
torchzero/modules/adaptive/adagrad.py
torchzero/modules/adaptive/adahessian.py
torchzero/modules/adaptive/adam.py
torchzero/modules/adaptive/adan.py
torchzero/modules/adaptive/adaptive_heavyball.py
torchzero/modules/adaptive/aegd.py
torchzero/modules/adaptive/esgd.py
torchzero/modules/adaptive/ggt.py
torchzero/modules/adaptive/lion.py
torchzero/modules/adaptive/lre_optimizers.py
torchzero/modules/adaptive/mars.py
torchzero/modules/adaptive/matrix_momentum.py
torchzero/modules/adaptive/msam.py
torchzero/modules/adaptive/muon.py
torchzero/modules/adaptive/natural_gradient.py
torchzero/modules/adaptive/orthograd.py
torchzero/modules/adaptive/rmsprop.py
torchzero/modules/adaptive/rprop.py
torchzero/modules/adaptive/sam.py
torchzero/modules/adaptive/shampoo.py
torchzero/modules/adaptive/soap.py
torchzero/modules/adaptive/sophia_h.py
torchzero/modules/adaptive/psgd/__init__.py
torchzero/modules/adaptive/psgd/_psgd_utils.py
torchzero/modules/adaptive/psgd/psgd.py
torchzero/modules/adaptive/psgd/psgd_dense_newton.py
torchzero-0.4.3.dist-info/METADATA
torchzero-0.4.3.dist-info/WHEEL
torchzero-0.4.3.dist-info/top_level.txt
torchzero-0.4.3.dist-info/RECORD
