Metadata-Version: 2.4
Name: torchzero
Version: 0.4.3
Summary: Modular optimization library for PyTorch.
Author-email: Ivan Nikishev <nkshv2@gmail.com>
Project-URL: Homepage, https://github.com/inikishev/torchzero
Project-URL: Repository, https://github.com/inikishev/torchzero
Project-URL: Issues, https://github.com/inikishev/torchzero/isses
Keywords: optimization,optimizers,torch,neural networks,zeroth order,second order
Requires-Python: >=3.10
Requires-Dist: torch
Requires-Dist: numpy
Requires-Dist: typing_extensions
